craigapts/__init__.py
craigapts/data.py
craigapts/search.py
craigapts-2020.3.16.dist-info/LICENSE.txt
craigapts-2020.3.16.dist-info/METADATA
craigapts-2020.3.16.dist-info/WHEEL
craigapts-2020.3.16.dist-info/top_level.txt
craigapts-2020.3.16.dist-info/RECORD
