Metadata-Version: 2.1
Name: craigapts
Version: 2020.3.16
Summary: Python package for scraping apartment data from Craigslist.
Home-page: https://gitlab.com/everetr/craigapts
Author: Everet Rummel
Author-email: 
License: LICENSE.txt
Platform: UNKNOWN
Classifier: Development Status :: 1 - Planning
Classifier: License :: OSI Approved :: GNU General Public License v3 (GPLv3)
Classifier: Natural Language :: English
Classifier: Programming Language :: Python
Classifier: Programming Language :: Python :: 3
Classifier: Programming Language :: Python :: 3.7
Requires-Python: >=3.7.0
Requires-Dist: beautifulsoup4 (>=4.8.2)
Requires-Dist: pandas (>=1.0.1)
Requires-Dist: requests (>=2.23.0)
